{"expansion":"expansion-6219","updated":"2026-07-14T02:44:29+0200","cards":[{"id":837230,"name":"Bulbasaur [Leech Seed | 151]","low":0.2,"trend":0,"avg1":null,"avg7":null,"avg30":null,"trend_holo":1.76,"low_holo":0.2},{"id":837231,"name":"Bulbasaur [Leech Seed | 151]","low":9,"trend":38.99,"avg1":38.99,"avg7":38.99,"avg30":38.99,"trend_holo":22.95,"low_holo":9},{"id":837232,"name":"Ivysaur [Leech Seed | Vine Whip | 151]","low":9.95,"trend":29.95,"avg1":29.95,"avg7":29.95,"avg30":29.95,"trend_holo":20.17,"low_holo":9.95},{"id":837233,"name":"Ivysaur [Leech Seed | Vine Whip | 151]","low":0.09,"trend":0,"avg1":null,"avg7":null,"avg30":null,"trend_holo":0.56,"low_holo":0.09},{"id":837234,"name":"Charmander [Blazing Destruction | Steady Firebreathing]","low":0.27,"trend":0,"avg1":null,"avg7":null,"avg30":null,"trend_holo":1.09,"low_holo":0.27},{"id":837235,"name":"Charmander [Blazing Destruction | Steady Firebreathing]","low":10,"trend":0,"avg1":null,"avg7":null,"avg30":null,"trend_holo":24.7,"low_holo":10},{"id":837236,"name":"Charmeleon [Combustion | Fire Blast]","low":3.99,"trend":0,"avg1":null,"avg7":null,"avg30":null,"trend_holo":16.76,"low_holo":3.99},{"id":837237,"name":"Charmeleon [Combustion | Fire Blast]","low":0.03,"trend":0,"avg1":null,"avg7":null,"avg30":null,"trend_holo":0.99,"low_holo":0.03},{"id":837238,"name":"Squirtle [Withdraw | Skull Bash]","low":0.05,"trend":0,"avg1":null,"avg7":null,"avg30":null,"trend_holo":1.51,"low_holo":0.05},{"id":837239,"name":"Squirtle [Withdraw | Skull Bash]","low":16.99,"trend":0,"avg1":null,"avg7":null,"avg30":null,"trend_holo":33.68,"low_holo":16.99},{"id":837240,"name":"Wartortle [Free Diving | Spinning Attack]","low":6.49,"trend":12,"avg1":12,"avg7":12,"avg30":12,"trend_holo":12.83,"low_holo":6.49},{"id":837241,"name":"Wartortle [Free Diving | Spinning Attack]","low":0.1,"trend":0,"avg1":null,"avg7":null,"avg30":null,"trend_holo":0.97,"low_holo":0.1},{"id":837242,"name":"Caterpie [Leaf Munch]","low":0.29,"trend":0.99,"avg1":0.99,"avg7":0.99,"avg30":0.99,"trend_holo":0.83,"low_holo":0.29},{"id":837243,"name":"Caterpie [Leaf Munch]","low":12.9,"trend":0,"avg1":null,"avg7":null,"avg30":null,"trend_holo":9.94,"low_holo":12.9},{"id":837244,"name":"Metapod [Tackle | Defensive Posture]","low":7.5,"trend":0,"avg1":null,"avg7":null,"avg30":null,"trend_holo":11.65,"low_holo":7.5},{"id":837245,"name":"Metapod [Tackle | Defensive Posture]","low":0.03,"trend":0,"avg1":null,"avg7":null,"avg30":null,"trend_holo":0.38,"low_holo":0.03},{"id":837246,"name":"Butterfree [Whirlwind | Bye Bye Flight]","low":0.49,"trend":0,"avg1":null,"avg7":null,"avg30":null,"trend_holo":0.95,"low_holo":0.49},{"id":837247,"name":"Butterfree [Whirlwind | Bye Bye Flight]","low":12,"trend":0,"avg1":null,"avg7":null,"avg30":null,"trend_holo":15.5,"low_holo":12},{"id":837248,"name":"Weedle [Ram | Bug Bite]","low":9,"trend":0,"avg1":null,"avg7":null,"avg30":null,"trend_holo":15.54,"low_holo":9},{"id":837249,"name":"Weedle [Ram | Bug Bite]","low":0.02,"trend":0.1,"avg1":0.1,"avg7":0.1,"avg30":0.1,"trend_holo":0.39,"low_holo":0.02},{"id":837250,"name":"Kakuna [Cocoon Cover | Zzzt]","low":0.04,"trend":0,"avg1":null,"avg7":null,"avg30":null,"trend_holo":0.21,"low_holo":0.04},{"id":837251,"name":"Kakuna [Cocoon Cover | Zzzt]","low":1.5,"trend":0,"avg1":null,"avg7":null,"avg30":null,"trend_holo":12.65,"low_holo":1.5},{"id":837252,"name":"Beedrill [Nadir Needle | Pierce]","low":9,"trend":0,"avg1":null,"avg7":null,"avg30":null,"trend_holo":12.64,"low_holo":9},{"id":837253,"name":"Beedrill [Nadir Needle | Pierce]","low":0.2,"trend":0,"avg1":null,"avg7":null,"avg30":null,"trend_holo":1.22,"low_holo":0.2},{"id":837254,"name":"Pidgey [Call for Family | Tackle]","low":0.05,"trend":0,"avg1":null,"avg7":null,"avg30":null,"trend_holo":0.32,"low_holo":0.05},{"id":837255,"name":"Pidgey [Call for Family | Tackle]","low":5,"trend":0,"avg1":null,"avg7":null,"avg30":null,"trend_holo":13.24,"low_holo":5},{"id":837256,"name":"Pidgeotto [Flap]","low":3.89,"trend":0,"avg1":null,"avg7":null,"avg30":null,"trend_holo":9.53,"low_holo":3.89},{"id":837257,"name":"Pidgeotto [Flap]","low":0.02,"trend":0,"avg1":null,"avg7":null,"avg30":null,"trend_holo":0.36,"low_holo":0.02},{"id":837258,"name":"Pidgeot [Flap | Fly]","low":0.1,"trend":0,"avg1":null,"avg7":null,"avg30":null,"trend_holo":1.04,"low_holo":0.1},{"id":837259,"name":"Pidgeot [Flap | Fly]","low":9,"trend":0,"avg1":null,"avg7":null,"avg30":null,"trend_holo":13.67,"low_holo":9},{"id":837260,"name":"Rattata [Gnaw the Wound]","low":4.47,"trend":4,"avg1":4,"avg7":4,"avg30":4,"trend_holo":12.03,"low_holo":4.47},{"id":837261,"name":"Rattata [Gnaw the Wound]","low":0.05,"trend":0,"avg1":null,"avg7":null,"avg30":null,"trend_holo":0.74,"low_holo":0.05},{"id":837262,"name":"Raticate [Second Bite]","low":0.1,"trend":0,"avg1":null,"avg7":null,"avg30":null,"trend_holo":0.58,"low_holo":0.1},{"id":837263,"name":"Raticate [Second Bite]","low":8,"trend":0,"avg1":null,"avg7":null,"avg30":null,"trend_holo":21.52,"low_holo":8},{"id":837264,"name":"Spearow [Evolutionary Advantage | Speed Dive]","low":3.75,"trend":0,"avg1":null,"avg7":null,"avg30":null,"trend_holo":9.37,"low_holo":3.75},{"id":837265,"name":"Spearow [Evolutionary Advantage | Speed Dive]","low":0.02,"trend":0,"avg1":null,"avg7":null,"avg30":null,"trend_holo":0.26,"low_holo":0.02},{"id":837267,"name":"Fearow [Beak Catch | Speed Dive]","low":0.03,"trend":0,"avg1":null,"avg7":null,"avg30":null,"trend_holo":0.37,"low_holo":0.03},{"id":837268,"name":"Fearow [Beak Catch | Speed Dive]","low":2.5,"trend":0,"avg1":null,"avg7":null,"avg30":null,"trend_holo":5.46,"low_holo":2.5},{"id":837269,"name":"Ekans [Acid Spray]","low":5,"trend":0,"avg1":null,"avg7":null,"avg30":null,"trend_holo":7.99,"low_holo":5},{"id":837270,"name":"Ekans [Acid Spray]","low":0.02,"trend":0,"avg1":null,"avg7":null,"avg30":null,"trend_holo":0.15,"low_holo":0.02},{"id":837271,"name":"Pikachu [Charge | Pika Punch]","low":0.4,"trend":1.49,"avg1":1.49,"avg7":1.49,"avg30":1.49,"trend_holo":2.16,"low_holo":0.4},{"id":837272,"name":"Pikachu [Charge | Pika Punch]","low":49.5,"trend":0,"avg1":null,"avg7":null,"avg30":null,"trend_holo":174.3,"low_holo":49.5},{"id":837273,"name":"Raichu [Electrical Grounding | Thunder]","low":5.99,"trend":0,"avg1":null,"avg7":null,"avg30":null,"trend_holo":12.01,"low_holo":5.99},{"id":837274,"name":"Raichu [Electrical Grounding | Thunder]","low":0.5,"trend":0,"avg1":null,"avg7":null,"avg30":null,"trend_holo":1.03,"low_holo":0.5},{"id":837275,"name":"Sandshrew [Sand Screen | Scratch]","low":0.02,"trend":0.99,"avg1":0.99,"avg7":0.99,"avg30":0.99,"trend_holo":0.54,"low_holo":0.02},{"id":837276,"name":"Sandshrew [Sand Screen | Scratch]","low":3,"trend":0,"avg1":null,"avg7":null,"avg30":null,"trend_holo":9.94,"low_holo":3},{"id":837277,"name":"Sandslash [Rumble | Spike Rend]","low":9.9,"trend":0,"avg1":null,"avg7":null,"avg30":null,"trend_holo":13.17,"low_holo":9.9},{"id":837278,"name":"Sandslash [Rumble | Spike Rend]","low":0.02,"trend":0,"avg1":null,"avg7":null,"avg30":null,"trend_holo":0.68,"low_holo":0.02},{"id":837279,"name":"Nidoran [F] [Poison Horn]","low":0.02,"trend":0,"avg1":null,"avg7":null,"avg30":null,"trend_holo":0.39,"low_holo":0.02},{"id":837280,"name":"Nidoran [F] [Poison Horn]","low":3,"trend":0,"avg1":null,"avg7":null,"avg30":null,"trend_holo":11.62,"low_holo":3},{"id":837281,"name":"Nidorina [Fetch Family | Sharp Fang]","low":1,"trend":0,"avg1":null,"avg7":null,"avg30":null,"trend_holo":9.35,"low_holo":1},{"id":837282,"name":"Nidorina [Fetch Family | Sharp Fang]","low":0.02,"trend":0,"avg1":null,"avg7":null,"avg30":null,"trend_holo":0.27,"low_holo":0.02},{"id":837283,"name":"Nidoqueen [Queen Press | Lunge Out]","low":0.02,"trend":0,"avg1":null,"avg7":null,"avg30":null,"trend_holo":0.53,"low_holo":0.02},{"id":837284,"name":"Nidoqueen [Queen Press | Lunge Out]","low":4,"trend":0,"avg1":null,"avg7":null,"avg30":null,"trend_holo":11.22,"low_holo":4},{"id":837285,"name":"Nidoran [M] [Horn Attack]","low":3.5,"trend":0,"avg1":null,"avg7":null,"avg30":null,"trend_holo":7.19,"low_holo":3.5},{"id":837286,"name":"Nidoran [M] [Horn Attack]","low":0.02,"trend":0,"avg1":null,"avg7":null,"avg30":null,"trend_holo":0.27,"low_holo":0.02},{"id":837287,"name":"Nidorino [Sharp Fang | Superpowered Horns]","low":0.05,"trend":0,"avg1":null,"avg7":null,"avg30":null,"trend_holo":0.3,"low_holo":0.05},{"id":837288,"name":"Nidorino [Sharp Fang | Superpowered Horns]","low":6,"trend":0,"avg1":null,"avg7":null,"avg30":null,"trend_holo":17.21,"low_holo":6},{"id":837289,"name":"Nidoking [Enthusiastic King | Venom Impact]","low":5.99,"trend":0,"avg1":null,"avg7":null,"avg30":null,"trend_holo":11.48,"low_holo":5.99},{"id":837290,"name":"Nidoking [Enthusiastic King | Venom Impact]","low":0.4,"trend":1.69,"avg1":1.69,"avg7":1.69,"avg30":1.69,"trend_holo":1.63,"low_holo":0.4},{"id":837291,"name":"Clefairy [Moon-Viewing Invitation | Smack]","low":0.15,"trend":0.99,"avg1":0.99,"avg7":0.99,"avg30":0.99,"trend_holo":0.75,"low_holo":0.15},{"id":837292,"name":"Clefairy [Moon-Viewing Invitation | Smack]","low":12.48,"trend":0,"avg1":null,"avg7":null,"avg30":null,"trend_holo":23.47,"low_holo":12.48},{"id":837293,"name":"Clefable [Follow Me | More Moon]","low":15,"trend":0,"avg1":null,"avg7":null,"avg30":null,"trend_holo":20.01,"low_holo":15},{"id":837294,"name":"Clefable [Follow Me | More Moon]","low":0.18,"trend":0,"avg1":null,"avg7":null,"avg30":null,"trend_holo":0.86,"low_holo":0.18},{"id":837295,"name":"Vulpix [Super Singe]","low":0.02,"trend":0,"avg1":null,"avg7":null,"avg30":null,"trend_holo":0.41,"low_holo":0.02},{"id":837296,"name":"Vulpix [Super Singe]","low":4.95,"trend":0,"avg1":null,"avg7":null,"avg30":null,"trend_holo":6.94,"low_holo":4.95},{"id":837297,"name":"Jigglypuff [Lead | Stompy Stomp]","low":4.7,"trend":0,"avg1":null,"avg7":null,"avg30":null,"trend_holo":14.64,"low_holo":4.7},{"id":837298,"name":"Jigglypuff [Lead | Stompy Stomp]","low":0.04,"trend":0,"avg1":null,"avg7":null,"avg30":null,"trend_holo":0.45,"low_holo":0.04},{"id":837299,"name":"Zubat [Revealing Echo | Bite]","low":0.1,"trend":0,"avg1":null,"avg7":null,"avg30":null,"trend_holo":0.72,"low_holo":0.1},{"id":837300,"name":"Zubat [Revealing Echo | Bite]","low":6,"trend":0,"avg1":null,"avg7":null,"avg30":null,"trend_holo":10.64,"low_holo":6},{"id":837301,"name":"Golbat [Skill Dive]","low":4.5,"trend":0,"avg1":null,"avg7":null,"avg30":null,"trend_holo":17.32,"low_holo":4.5},{"id":837302,"name":"Golbat [Skill Dive]","low":0.03,"trend":0,"avg1":null,"avg7":null,"avg30":null,"trend_holo":0.5,"low_holo":0.03},{"id":837303,"name":"Oddish [Razor Leaf]","low":0.02,"trend":0,"avg1":null,"avg7":null,"avg30":null,"trend_holo":0.25,"low_holo":0.02},{"id":837304,"name":"Oddish [Razor Leaf]","low":6,"trend":0,"avg1":null,"avg7":null,"avg30":null,"trend_holo":11.67,"low_holo":6},{"id":837305,"name":"Gloom [Semi-Blooming Energy | Drool]","low":9.99,"trend":0,"avg1":null,"avg7":null,"avg30":null,"trend_holo":11.16,"low_holo":9.99},{"id":837306,"name":"Gloom [Semi-Blooming Energy | Drool]","low":0.04,"trend":0,"avg1":null,"avg7":null,"avg30":null,"trend_holo":0.32,"low_holo":0.04},{"id":837307,"name":"Vileplume [Fully Blooming Energy | Solar Beam]","low":0.1,"trend":0,"avg1":null,"avg7":null,"avg30":null,"trend_holo":0.92,"low_holo":0.1},{"id":837308,"name":"Vileplume [Fully Blooming Energy | Solar Beam]","low":9,"trend":0,"avg1":null,"avg7":null,"avg30":null,"trend_holo":11.99,"low_holo":9},{"id":837309,"name":"Paras [Stampede | Spore Ball]","low":3.99,"trend":0,"avg1":null,"avg7":null,"avg30":null,"trend_holo":7.13,"low_holo":3.99},{"id":837310,"name":"Paras [Stampede | Spore Ball]","low":0.18,"trend":0,"avg1":null,"avg7":null,"avg30":null,"trend_holo":0.83,"low_holo":0.18},{"id":837311,"name":"Parasect [Spread Filaments | Claw Slash]","low":0.15,"trend":0,"avg1":null,"avg7":null,"avg30":null,"trend_holo":0.8,"low_holo":0.15},{"id":837312,"name":"Parasect [Spread Filaments | Claw Slash]","low":6.5,"trend":0,"avg1":null,"avg7":null,"avg30":null,"trend_holo":12.67,"low_holo":6.5},{"id":837313,"name":"Venonat [Gnaw | Beam]","low":5,"trend":0,"avg1":null,"avg7":null,"avg30":null,"trend_holo":12.15,"low_holo":5},{"id":837314,"name":"Venonat [Gnaw | Beam]","low":0.12,"trend":0,"avg1":null,"avg7":null,"avg30":null,"trend_holo":0.69,"low_holo":0.12},{"id":837315,"name":"Venomoth [Perplexing Powder | Speed Wing]","low":0.1,"trend":0,"avg1":null,"avg7":null,"avg30":null,"trend_holo":0.76,"low_holo":0.1},{"id":837316,"name":"Venomoth [Perplexing Powder | Speed Wing]","low":5.89,"trend":0,"avg1":null,"avg7":null,"avg30":null,"trend_holo":10,"low_holo":5.89},{"id":837317,"name":"Diglett [Headbutt Bounce | Mud-Slap]","low":7.45,"trend":0,"avg1":null,"avg7":null,"avg30":null,"trend_holo":14.01,"low_holo":7.45},{"id":837318,"name":"Diglett [Headbutt Bounce | Mud-Slap]","low":0.05,"trend":0,"avg1":null,"avg7":null,"avg30":null,"trend_holo":0.47,"low_holo":0.05},{"id":837319,"name":"Dugtrio [Headbutt Bounce | Mud Bomb]","low":0.03,"trend":0,"avg1":null,"avg7":null,"avg30":null,"trend_holo":0.39,"low_holo":0.03},{"id":837320,"name":"Dugtrio [Headbutt Bounce | Mud Bomb]","low":8.99,"trend":0,"avg1":null,"avg7":null,"avg30":null,"trend_holo":14.17,"low_holo":8.99},{"id":837321,"name":"Meowth [Come Here Right Meow | Dig Claws]","low":6,"trend":0,"avg1":null,"avg7":null,"avg30":null,"trend_holo":8.9,"low_holo":6},{"id":837322,"name":"Meowth [Come Here Right Meow | Dig Claws]","low":0.05,"trend":0.99,"avg1":0.99,"avg7":0.99,"avg30":0.99,"trend_holo":0.4,"low_holo":0.05},{"id":837323,"name":"Persian [Rocket Call | Slash]","low":0.09,"trend":0,"avg1":null,"avg7":null,"avg30":null,"trend_holo":0.24,"low_holo":0.09},{"id":837324,"name":"Persian [Rocket Call | Slash]","low":5,"trend":0,"avg1":null,"avg7":null,"avg30":null,"trend_holo":7.85,"low_holo":5},{"id":837325,"name":"Psyduck [Overthinking | Water Gun]","low":70,"trend":0,"avg1":null,"avg7":null,"avg30":null,"trend_holo":123.05,"low_holo":70},{"id":837326,"name":"Psyduck [Overthinking | Water Gun]","low":1,"trend":0,"avg1":null,"avg7":null,"avg30":null,"trend_holo":4.45,"low_holo":1},{"id":837327,"name":"Golduck [Aquatic Rescue | Super Splash]","low":0.1,"trend":0.99,"avg1":0.99,"avg7":0.99,"avg30":0.99,"trend_holo":0.61,"low_holo":0.1},{"id":837328,"name":"Golduck [Aquatic Rescue | Super Splash]","low":8.5,"trend":0,"avg1":null,"avg7":null,"avg30":null,"trend_holo":14.6,"low_holo":8.5},{"id":837329,"name":"Mankey [Thrash]","low":5.95,"trend":0,"avg1":null,"avg7":null,"avg30":null,"trend_holo":11.32,"low_holo":5.95},{"id":837330,"name":"Mankey [Thrash]","low":0.1,"trend":0.99,"avg1":0.99,"avg7":0.99,"avg30":0.99,"trend_holo":0.82,"low_holo":0.1},{"id":837331,"name":"Primeape [Rant and Rave | Raging Smash]","low":0.3,"trend":0,"avg1":null,"avg7":null,"avg30":null,"trend_holo":0.56,"low_holo":0.3},{"id":837332,"name":"Primeape [Rant and Rave | Raging Smash]","low":9,"trend":0,"avg1":null,"avg7":null,"avg30":null,"trend_holo":11.42,"low_holo":9},{"id":837333,"name":"Growlithe [Vaporize]","low":4.95,"trend":0,"avg1":null,"avg7":null,"avg30":null,"trend_holo":29.03,"low_holo":4.95},{"id":837334,"name":"Growlithe [Vaporize]","low":0.25,"trend":0,"avg1":null,"avg7":null,"avg30":null,"trend_holo":0.66,"low_holo":0.25},{"id":837335,"name":"Arcanine [Torrid Torrent | Dynamite Fang]","low":0.15,"trend":0,"avg1":null,"avg7":null,"avg30":null,"trend_holo":1.1,"low_holo":0.15},{"id":837336,"name":"Arcanine [Torrid Torrent | Dynamite Fang]","low":15,"trend":0,"avg1":null,"avg7":null,"avg30":null,"trend_holo":21.8,"low_holo":15},{"id":837337,"name":"Poliwag [Bubble | 151]","low":10,"trend":0,"avg1":null,"avg7":null,"avg30":null,"trend_holo":19.19,"low_holo":10},{"id":837338,"name":"Poliwag [Bubble | 151]","low":0.09,"trend":0,"avg1":null,"avg7":null,"avg30":null,"trend_holo":0.54,"low_holo":0.09},{"id":837339,"name":"Poliwhirl [Wave Splash | Frog Hop]","low":0.02,"trend":0,"avg1":null,"avg7":null,"avg30":null,"trend_holo":0.31,"low_holo":0.02},{"id":837340,"name":"Poliwhirl [Wave Splash | Frog Hop]","low":10,"trend":0,"avg1":null,"avg7":null,"avg30":null,"trend_holo":14.88,"low_holo":10},{"id":837342,"name":"Poliwrath [Bubble Beam | Heroic Punch]","low":9,"trend":0,"avg1":null,"avg7":null,"avg30":null,"trend_holo":19.6,"low_holo":9},{"id":837343,"name":"Poliwrath [Bubble Beam | Heroic Punch]","low":0.2,"trend":0,"avg1":null,"avg7":null,"avg30":null,"trend_holo":0.79,"low_holo":0.2},{"id":837344,"name":"Abra [Psyshot]","low":0.02,"trend":0,"avg1":null,"avg7":null,"avg30":null,"trend_holo":0.25,"low_holo":0.02},{"id":837345,"name":"Abra [Psyshot]","low":2.6,"trend":0,"avg1":null,"avg7":null,"avg30":null,"trend_holo":7.7,"low_holo":2.6},{"id":837346,"name":"Kadabra [Teleportation Attack]","low":4.5,"trend":0,"avg1":null,"avg7":null,"avg30":null,"trend_holo":6.41,"low_holo":4.5},{"id":837347,"name":"Kadabra [Teleportation Attack]","low":0.02,"trend":0,"avg1":null,"avg7":null,"avg30":null,"trend_holo":0.41,"low_holo":0.02},{"id":837348,"name":"Machop [Mountain Mashing | Punch]","low":0.1,"trend":0,"avg1":null,"avg7":null,"avg30":null,"trend_holo":0.62,"low_holo":0.1},{"id":837349,"name":"Machop [Mountain Mashing | Punch]","low":4,"trend":0,"avg1":null,"avg7":null,"avg30":null,"trend_holo":11.09,"low_holo":4},{"id":837350,"name":"Machoke [Mountain Ramming]","low":3.5,"trend":0,"avg1":null,"avg7":null,"avg30":null,"trend_holo":9.2,"low_holo":3.5},{"id":837351,"name":"Machoke [Mountain Ramming]","low":0.25,"trend":0,"avg1":null,"avg7":null,"avg30":null,"trend_holo":0.8,"low_holo":0.25},{"id":837352,"name":"Machamp [Guts | Mountain Chopping]","low":0.15,"trend":0,"avg1":null,"avg7":null,"avg30":null,"trend_holo":0.84,"low_holo":0.15},{"id":837353,"name":"Machamp [Guts | Mountain Chopping]","low":11,"trend":0,"avg1":null,"avg7":null,"avg30":null,"trend_holo":13.48,"low_holo":11},{"id":837354,"name":"Bellsprout [Cut | Bind Down]","low":8.99,"trend":0,"avg1":null,"avg7":null,"avg30":null,"trend_holo":13.61,"low_holo":8.99},{"id":837355,"name":"Bellsprout [Cut | Bind Down]","low":0.05,"trend":0.99,"avg1":0.99,"avg7":0.99,"avg30":0.99,"trend_holo":0.45,"low_holo":0.05},{"id":837356,"name":"Weepinbell [Cut | Spray Fluid]","low":0.05,"trend":0,"avg1":null,"avg7":null,"avg30":null,"trend_holo":0.28,"low_holo":0.05},{"id":837357,"name":"Weepinbell [Cut | Spray Fluid]","low":4,"trend":0,"avg1":null,"avg7":null,"avg30":null,"trend_holo":11.87,"low_holo":4},{"id":837358,"name":"Victreebel [Spit Up | Slow-Acting Acid]","low":5,"trend":0,"avg1":null,"avg7":null,"avg30":null,"trend_holo":10.82,"low_holo":5},{"id":837359,"name":"Victreebel [Spit Up | Slow-Acting Acid]","low":0.2,"trend":0,"avg1":null,"avg7":null,"avg30":null,"trend_holo":0.62,"low_holo":0.2},{"id":837370,"name":"Tentacool [Tingle | Watering]","low":0.1,"trend":0,"avg1":null,"avg7":null,"avg30":null,"trend_holo":0.6,"low_holo":0.1},{"id":837372,"name":"Tentacool [Tingle | Watering]","low":5.49,"trend":0,"avg1":null,"avg7":null,"avg30":null,"trend_holo":10.09,"low_holo":5.49},{"id":837373,"name":"Tentacruel [Poisonous Whip | Tentacular Panic]","low":6.5,"trend":0,"avg1":null,"avg7":null,"avg30":null,"trend_holo":10.48,"low_holo":6.5},{"id":837374,"name":"Tentacruel [Poisonous Whip | Tentacular Panic]","low":0.2,"trend":0,"avg1":null,"avg7":null,"avg30":null,"trend_holo":0.64,"low_holo":0.2},{"id":837375,"name":"Geodude [Stiffen | Knuckle Punch]","low":0.04,"trend":0,"avg1":null,"avg7":null,"avg30":null,"trend_holo":0.3,"low_holo":0.04},{"id":837376,"name":"Geodude [Stiffen | Knuckle Punch]","low":3,"trend":0,"avg1":null,"avg7":null,"avg30":null,"trend_holo":4.32,"low_holo":3},{"id":837377,"name":"Graveler [Rock Cannon | Heavy Impact]","low":2.8,"trend":0,"avg1":null,"avg7":null,"avg30":null,"trend_holo":8.15,"low_holo":2.8},{"id":837378,"name":"Graveler [Rock Cannon | Heavy Impact]","low":0.05,"trend":0,"avg1":null,"avg7":null,"avg30":null,"trend_holo":0.43,"low_holo":0.05},{"id":837379,"name":"Ponyta [Collect | Flop]","low":0.05,"trend":0,"avg1":null,"avg7":null,"avg30":null,"trend_holo":0.61,"low_holo":0.05},{"id":837380,"name":"Ponyta [Collect | Flop]","low":5,"trend":0,"avg1":null,"avg7":null,"avg30":null,"trend_holo":11.95,"low_holo":5},{"id":837382,"name":"Rapidash [Singe | Mach Turn]","low":9.99,"trend":0,"avg1":null,"avg7":null,"avg30":null,"trend_holo":15.46,"low_holo":9.99},{"id":837383,"name":"Rapidash [Singe | Mach Turn]","low":0.14,"trend":0,"avg1":null,"avg7":null,"avg30":null,"trend_holo":0.63,"low_holo":0.14},{"id":837386,"name":"Slowpoke [Sea Bathing | Headbutt]","low":0.1,"trend":0.99,"avg1":0.99,"avg7":0.99,"avg30":0.99,"trend_holo":1.34,"low_holo":0.1},{"id":837387,"name":"Slowpoke [Sea Bathing | Headbutt]","low":9,"trend":0,"avg1":null,"avg7":null,"avg30":null,"trend_holo":42.43,"low_holo":9},{"id":837388,"name":"Slowbro [Big Yawn | Laid-Back Tackle]","low":11,"trend":0,"avg1":null,"avg7":null,"avg30":null,"trend_holo":27.97,"low_holo":11},{"id":837389,"name":"Slowbro [Big Yawn | Laid-Back Tackle]","low":0.1,"trend":0,"avg1":null,"avg7":null,"avg30":null,"trend_holo":0.88,"low_holo":0.1},{"id":837390,"name":"Magnemite [Tiny Charge | Big Explosion]","low":0.1,"trend":0.2,"avg1":0.2,"avg7":0.2,"avg30":0.2,"trend_holo":0.58,"low_holo":0.1},{"id":837391,"name":"Magnemite [Tiny Charge | Big Explosion]","low":4,"trend":0,"avg1":null,"avg7":null,"avg30":null,"trend_holo":10.12,"low_holo":4},{"id":837392,"name":"Magneton [Junk Magnet | Head Bolt]","low":6,"trend":0,"avg1":null,"avg7":null,"avg30":null,"trend_holo":17.21,"low_holo":6},{"id":837393,"name":"Magneton [Junk Magnet | Head Bolt]","low":0.1,"trend":0,"avg1":null,"avg7":null,"avg30":null,"trend_holo":0.45,"low_holo":0.1},{"id":837394,"name":"Farfetch'd [Package Deal | Leek Clobber]","low":0.08,"trend":0.99,"avg1":0.99,"avg7":0.99,"avg30":0.99,"trend_holo":0.83,"low_holo":0.08},{"id":837395,"name":"Farfetch'd [Package Deal | Leek Clobber]","low":3,"trend":0,"avg1":null,"avg7":null,"avg30":null,"trend_holo":9.55,"low_holo":3},{"id":837396,"name":"Doduo [Reckless Charge]","low":0.5,"trend":0,"avg1":null,"avg7":null,"avg30":null,"trend_holo":6.93,"low_holo":0.5},{"id":837397,"name":"Doduo [Reckless Charge]","low":0.02,"trend":0.02,"avg1":0.02,"avg7":0.02,"avg30":0.02,"trend_holo":0.28,"low_holo":0.02},{"id":837398,"name":"Dodrio [Zooming Draw | Ballistic Beak]","low":0.14,"trend":0,"avg1":null,"avg7":null,"avg30":null,"trend_holo":0.49,"low_holo":0.14},{"id":837399,"name":"Dodrio [Zooming Draw | Ballistic Beak]","low":2.5,"trend":0,"avg1":null,"avg7":null,"avg30":null,"trend_holo":3.87,"low_holo":2.5},{"id":837400,"name":"Seel [Chilly]","low":5.5,"trend":0,"avg1":null,"avg7":null,"avg30":null,"trend_holo":7.69,"low_holo":5.5},{"id":837401,"name":"Seel [Chilly]","low":0.1,"trend":0,"avg1":null,"avg7":null,"avg30":null,"trend_holo":0.4,"low_holo":0.1},{"id":837402,"name":"Dewgong [Dual Splash | Aurora Beam]","low":0.15,"trend":0,"avg1":null,"avg7":null,"avg30":null,"trend_holo":0.73,"low_holo":0.15},{"id":837403,"name":"Dewgong [Dual Splash | Aurora Beam]","low":4,"trend":0,"avg1":null,"avg7":null,"avg30":null,"trend_holo":10.68,"low_holo":4},{"id":837404,"name":"Grimer [Gummy Press]","low":8.99,"trend":0,"avg1":null,"avg7":null,"avg30":null,"trend_holo":14.52,"low_holo":8.99},{"id":837405,"name":"Grimer [Gummy Press]","low":0.15,"trend":0,"avg1":null,"avg7":null,"avg30":null,"trend_holo":0.74,"low_holo":0.15},{"id":837406,"name":"Muk [Sticky Jail | Sludge Bomb]","low":0.2,"trend":0,"avg1":null,"avg7":null,"avg30":null,"trend_holo":0.75,"low_holo":0.2},{"id":837407,"name":"Muk [Sticky Jail | Sludge Bomb]","low":4.4,"trend":14.99,"avg1":14.99,"avg7":14.99,"avg30":14.99,"trend_holo":11.94,"low_holo":4.4},{"id":837408,"name":"Shellder [Shell Press]","low":4.95,"trend":0,"avg1":null,"avg7":null,"avg30":null,"trend_holo":11.6,"low_holo":4.95},{"id":837409,"name":"Shellder [Shell Press]","low":0.09,"trend":0,"avg1":null,"avg7":null,"avg30":null,"trend_holo":0.62,"low_holo":0.09},{"id":837410,"name":"Cloyster [Protect Charge]","low":0.11,"trend":0,"avg1":null,"avg7":null,"avg30":null,"trend_holo":0.75,"low_holo":0.11},{"id":837411,"name":"Cloyster [Protect Charge]","low":4,"trend":0,"avg1":null,"avg7":null,"avg30":null,"trend_holo":11.71,"low_holo":4},{"id":837412,"name":"Gastly [Suffocating Gas]","low":14.5,"trend":0,"avg1":null,"avg7":null,"avg30":null,"trend_holo":44.18,"low_holo":14.5},{"id":837413,"name":"Gastly [Suffocating Gas]","low":0.2,"trend":0,"avg1":null,"avg7":null,"avg30":null,"trend_holo":1.36,"low_holo":0.2},{"id":837414,"name":"Haunter [Spirit Return | Mumble]","low":0.99,"trend":0,"avg1":null,"avg7":null,"avg30":null,"trend_holo":3.49,"low_holo":0.99},{"id":837415,"name":"Haunter [Spirit Return | Mumble]","low":14.99,"trend":96.58,"avg1":96.58,"avg7":96.58,"avg30":96.58,"trend_holo":69.11,"low_holo":14.99},{"id":837416,"name":"Gengar [Poltergeist | Hollow Dive]","low":93.95,"trend":0,"avg1":null,"avg7":null,"avg30":null,"trend_holo":538.24,"low_holo":93.95},{"id":837417,"name":"Gengar [Poltergeist | Hollow Dive]","low":5,"trend":0,"avg1":null,"avg7":null,"avg30":null,"trend_holo":12.21,"low_holo":5},{"id":837418,"name":"Onix [Thumpalanche | Heavy Impact]","low":0.02,"trend":0,"avg1":null,"avg7":null,"avg30":null,"trend_holo":0.3,"low_holo":0.02},{"id":837419,"name":"Onix [Thumpalanche | Heavy Impact]","low":1.8,"trend":0,"avg1":null,"avg7":null,"avg30":null,"trend_holo":13.64,"low_holo":1.8},{"id":837420,"name":"Drowzee [Zen Headbutt]","low":4,"trend":0,"avg1":null,"avg7":null,"avg30":null,"trend_holo":13.7,"low_holo":4},{"id":837421,"name":"Drowzee [Zen Headbutt]","low":0.15,"trend":0,"avg1":null,"avg7":null,"avg30":null,"trend_holo":0.53,"low_holo":0.15},{"id":837422,"name":"Hypno [Here for Hypnosis | Super Psy Bolt]","low":0.15,"trend":0,"avg1":null,"avg7":null,"avg30":null,"trend_holo":0.69,"low_holo":0.15},{"id":837423,"name":"Hypno [Here for Hypnosis | Super Psy Bolt]","low":4.99,"trend":0,"avg1":null,"avg7":null,"avg30":null,"trend_holo":9.84,"low_holo":4.99},{"id":837424,"name":"Krabby [Salt Water | Crabhammer]","low":10,"trend":0,"avg1":null,"avg7":null,"avg30":null,"trend_holo":12.39,"low_holo":10},{"id":837425,"name":"Krabby [Salt Water | Crabhammer]","low":0.04,"trend":0,"avg1":null,"avg7":null,"avg30":null,"trend_holo":0.53,"low_holo":0.04},{"id":837426,"name":"Kingler [Hammer Arm | Guillotine]","low":0.1,"trend":0,"avg1":null,"avg7":null,"avg30":null,"trend_holo":0.8,"low_holo":0.1},{"id":837427,"name":"Kingler [Hammer Arm | Guillotine]","low":7.99,"trend":0,"avg1":null,"avg7":null,"avg30":null,"trend_holo":11.24,"low_holo":7.99},{"id":837428,"name":"Voltorb [Tumbling Attack]","low":1.99,"trend":0,"avg1":null,"avg7":null,"avg30":null,"trend_holo":11.47,"low_holo":1.99},{"id":837429,"name":"Voltorb [Tumbling Attack]","low":0.02,"trend":0,"avg1":null,"avg7":null,"avg30":null,"trend_holo":0.37,"low_holo":0.02},{"id":837430,"name":"Electrode [Bang Boom Chain | Electro Ball]","low":0.05,"trend":0,"avg1":null,"avg7":null,"avg30":null,"trend_holo":0.44,"low_holo":0.05},{"id":837431,"name":"Electrode [Bang Boom Chain | Electro Ball]","low":3,"trend":0,"avg1":null,"avg7":null,"avg30":null,"trend_holo":7.85,"low_holo":3},{"id":837432,"name":"Exeggcute [Ball Roll]","low":6.99,"trend":0,"avg1":null,"avg7":null,"avg30":null,"trend_holo":12.72,"low_holo":6.99},{"id":837433,"name":"Exeggcute [Ball Roll]","low":0.08,"trend":0,"avg1":null,"avg7":null,"avg30":null,"trend_holo":0.75,"low_holo":0.08},{"id":837434,"name":"Exeggutor [Psychic | Hammer In]","low":0.13,"trend":0,"avg1":null,"avg7":null,"avg30":null,"trend_holo":0.73,"low_holo":0.13},{"id":837435,"name":"Exeggutor [Psychic | Hammer In]","low":4,"trend":0,"avg1":null,"avg7":null,"avg30":null,"trend_holo":7.24,"low_holo":4},{"id":837436,"name":"Cubone [Cheering Bone | Hit Twice]","low":39,"trend":0,"avg1":null,"avg7":null,"avg30":null,"trend_holo":59.39,"low_holo":39},{"id":837437,"name":"Cubone [Cheering Bone | Hit Twice]","low":0.09,"trend":0,"avg1":null,"avg7":null,"avg30":null,"trend_holo":0.34,"low_holo":0.09},{"id":837438,"name":"Marowak [Bone Throw | Boundless Power]","low":0.14,"trend":0.99,"avg1":0.99,"avg7":0.99,"avg30":0.99,"trend_holo":0.89,"low_holo":0.14},{"id":837439,"name":"Marowak [Bone Throw | Boundless Power]","low":8.49,"trend":0,"avg1":null,"avg7":null,"avg30":null,"trend_holo":11.02,"low_holo":8.49},{"id":837440,"name":"Hitmonlee [Twister Kick | Low Kick]","low":7.5,"trend":0,"avg1":null,"avg7":null,"avg30":null,"trend_holo":15.54,"low_holo":7.5},{"id":837441,"name":"Hitmonlee [Twister Kick | Low Kick]","low":0.34,"trend":0,"avg1":null,"avg7":null,"avg30":null,"trend_holo":0.88,"low_holo":0.34},{"id":837442,"name":"Hitmonchan [Counterattack | Excited Punch]","low":0.15,"trend":0,"avg1":null,"avg7":null,"avg30":null,"trend_holo":0.82,"low_holo":0.15},{"id":837443,"name":"Hitmonchan [Counterattack | Excited Punch]","low":9.98,"trend":0,"avg1":null,"avg7":null,"avg30":null,"trend_holo":11.12,"low_holo":9.98},{"id":837444,"name":"Lickitung [Tongue-Tied]","low":4,"trend":0,"avg1":null,"avg7":null,"avg30":null,"trend_holo":10.46,"low_holo":4},{"id":837445,"name":"Lickitung [Tongue-Tied]","low":0.09,"trend":1,"avg1":1,"avg7":1,"avg30":1,"trend_holo":0.29,"low_holo":0.09},{"id":837446,"name":"Koffing [Suspicious Gas]","low":0.07,"trend":0,"avg1":null,"avg7":null,"avg30":null,"trend_holo":0.77,"low_holo":0.07},{"id":837447,"name":"Koffing [Suspicious Gas]","low":9.89,"trend":0,"avg1":null,"avg7":null,"avg30":null,"trend_holo":10.41,"low_holo":9.89},{"id":837448,"name":"Weezing [Let's Have a Blast | Spinning Fumes]","low":8.95,"trend":0,"avg1":null,"avg7":null,"avg30":null,"trend_holo":19.83,"low_holo":8.95},{"id":837449,"name":"Weezing [Let's Have a Blast | Spinning Fumes]","low":0.04,"trend":0,"avg1":null,"avg7":null,"avg30":null,"trend_holo":0.78,"low_holo":0.04},{"id":837450,"name":"Rhyhorn [Push Down | Boulder Crush]","low":0.02,"trend":0,"avg1":null,"avg7":null,"avg30":null,"trend_holo":0.23,"low_holo":0.02},{"id":837451,"name":"Rhyhorn [Push Down | Boulder Crush]","low":8,"trend":0,"avg1":null,"avg7":null,"avg30":null,"trend_holo":9.48,"low_holo":8},{"id":837452,"name":"Rhydon [Wrack Down | Charismatic Drill]","low":2.6,"trend":0,"avg1":null,"avg7":null,"avg30":null,"trend_holo":5.68,"low_holo":2.6},{"id":837453,"name":"Rhydon [Wrack Down | Charismatic Drill]","low":0.02,"trend":0,"avg1":null,"avg7":null,"avg30":null,"trend_holo":0.29,"low_holo":0.02},{"id":837454,"name":"Chansey [Lucky Bonus | Gentle Slap]","low":0.2,"trend":0.05,"avg1":0.05,"avg7":0.05,"avg30":0.05,"trend_holo":0.88,"low_holo":0.2},{"id":837455,"name":"Chansey [Lucky Bonus | Gentle Slap]","low":2.9,"trend":0,"avg1":null,"avg7":null,"avg30":null,"trend_holo":6.59,"low_holo":2.9},{"id":837456,"name":"Tangela [Tactful Tangling]","low":4.5,"trend":0,"avg1":null,"avg7":null,"avg30":null,"trend_holo":10.45,"low_holo":4.5},{"id":837457,"name":"Tangela [Tactful Tangling]","low":0.05,"trend":0,"avg1":null,"avg7":null,"avg30":null,"trend_holo":0.96,"low_holo":0.05},{"id":837458,"name":"Horsea [Rain Splash | Sharp Fin]","low":0.25,"trend":0,"avg1":null,"avg7":null,"avg30":null,"trend_holo":0.91,"low_holo":0.25},{"id":837459,"name":"Horsea [Rain Splash | Sharp Fin]","low":4.99,"trend":0,"avg1":null,"avg7":null,"avg30":null,"trend_holo":11.97,"low_holo":4.99},{"id":837460,"name":"Seadra [Blinding Ink]","low":5,"trend":0,"avg1":null,"avg7":null,"avg30":null,"trend_holo":11.48,"low_holo":5},{"id":837461,"name":"Seadra [Blinding Ink]","low":0.3,"trend":0,"avg1":null,"avg7":null,"avg30":null,"trend_holo":0.89,"low_holo":0.3},{"id":837462,"name":"Goldeen [Triple Strike | Sprinkle Water]","low":0.1,"trend":0,"avg1":null,"avg7":null,"avg30":null,"trend_holo":0.92,"low_holo":0.1},{"id":837463,"name":"Goldeen [Triple Strike | Sprinkle Water]","low":7,"trend":0,"avg1":null,"avg7":null,"avg30":null,"trend_holo":7.94,"low_holo":7},{"id":837464,"name":"Seaking [Swim Freely | Aqua Horn]","low":10,"trend":0,"avg1":null,"avg7":null,"avg30":null,"trend_holo":13.32,"low_holo":10},{"id":837465,"name":"Seaking [Swim Freely | Aqua Horn]","low":0.2,"trend":0,"avg1":null,"avg7":null,"avg30":null,"trend_holo":0.79,"low_holo":0.2},{"id":837466,"name":"Staryu [Swift]","low":0.04,"trend":0,"avg1":null,"avg7":null,"avg30":null,"trend_holo":0.28,"low_holo":0.04},{"id":837467,"name":"Staryu [Swift]","low":3,"trend":0,"avg1":null,"avg7":null,"avg30":null,"trend_holo":3.43,"low_holo":3},{"id":837468,"name":"Starmie [Mysterious Comet | Speed Attack]","low":3.5,"trend":0,"avg1":null,"avg7":null,"avg30":null,"trend_holo":16.8,"low_holo":3.5},{"id":837469,"name":"Starmie [Mysterious Comet | Speed Attack]","low":0.15,"trend":0,"avg1":null,"avg7":null,"avg30":null,"trend_holo":1.16,"low_holo":0.15},{"id":837470,"name":"Mr. Mime [Mimic Barrier | Psypower]","low":0.05,"trend":0,"avg1":null,"avg7":null,"avg30":null,"trend_holo":0.51,"low_holo":0.05},{"id":837471,"name":"Mr. Mime [Mimic Barrier | Psypower]","low":5,"trend":0,"avg1":null,"avg7":null,"avg30":null,"trend_holo":13.25,"low_holo":5},{"id":837472,"name":"Scyther [Helpful Slash | Slicing Blade]","low":0.03,"trend":0,"avg1":null,"avg7":null,"avg30":null,"trend_holo":1.03,"low_holo":0.03},{"id":837473,"name":"Scyther [Helpful Slash | Slicing Blade]","low":3.95,"trend":0,"avg1":null,"avg7":null,"avg30":null,"trend_holo":12.65,"low_holo":3.95},{"id":837474,"name":"Electabuzz [Electro Combo | Light Punch]","low":0.06,"trend":0,"avg1":null,"avg7":null,"avg30":null,"trend_holo":0.31,"low_holo":0.06},{"id":837475,"name":"Electabuzz [Electro Combo | Light Punch]","low":4,"trend":0,"avg1":null,"avg7":null,"avg30":null,"trend_holo":11.79,"low_holo":4},{"id":837476,"name":"Magmar [Live Coal | Flare Combo]","low":0.07,"trend":0,"avg1":null,"avg7":null,"avg30":null,"trend_holo":0.32,"low_holo":0.07},{"id":837477,"name":"Magmar [Live Coal | Flare Combo]","low":5.99,"trend":0,"avg1":null,"avg7":null,"avg30":null,"trend_holo":17.03,"low_holo":5.99},{"id":837478,"name":"Pinsir [Vise Grip | Reckless Throw]","low":0.15,"trend":0,"avg1":null,"avg7":null,"avg30":null,"trend_holo":0.65,"low_holo":0.15},{"id":837479,"name":"Pinsir [Vise Grip | Reckless Throw]","low":3,"trend":0,"avg1":null,"avg7":null,"avg30":null,"trend_holo":13.96,"low_holo":3},{"id":837480,"name":"Tauros [Gather the Crew | Rage]","low":0.02,"trend":0,"avg1":null,"avg7":null,"avg30":null,"trend_holo":0.77,"low_holo":0.02},{"id":837481,"name":"Tauros [Gather the Crew | Rage]","low":1.25,"trend":0,"avg1":null,"avg7":null,"avg30":null,"trend_holo":18.66,"low_holo":1.25},{"id":837482,"name":"Magikarp [Splashy Splash]","low":0.18,"trend":0,"avg1":null,"avg7":null,"avg30":null,"trend_holo":1.11,"low_holo":0.18},{"id":837483,"name":"Magikarp [Splashy Splash]","low":30,"trend":0,"avg1":null,"avg7":null,"avg30":null,"trend_holo":57.46,"low_holo":30},{"id":837484,"name":"Gyarados [Untamed One | Hyper Beam]","low":0.3,"trend":0,"avg1":null,"avg7":null,"avg30":null,"trend_holo":1.63,"low_holo":0.3},{"id":837485,"name":"Gyarados [Untamed One | Hyper Beam]","low":19.49,"trend":0,"avg1":null,"avg7":null,"avg30":null,"trend_holo":66.48,"low_holo":19.49},{"id":837486,"name":"Lapras [Hop on My Back | Aqua Edge]","low":0.15,"trend":0,"avg1":null,"avg7":null,"avg30":null,"trend_holo":0.77,"low_holo":0.15},{"id":837487,"name":"Lapras [Hop on My Back | Aqua Edge]","low":4.5,"trend":0,"avg1":null,"avg7":null,"avg30":null,"trend_holo":20.28,"low_holo":4.5},{"id":837488,"name":"Ditto [Transformative Start | Splup]","low":0.19,"trend":0,"avg1":null,"avg7":null,"avg30":null,"trend_holo":1.39,"low_holo":0.19},{"id":837489,"name":"Ditto [Transformative Start | Splup]","low":8.99,"trend":0,"avg1":null,"avg7":null,"avg30":null,"trend_holo":14.16,"low_holo":8.99},{"id":837490,"name":"Eevee [Colorful Friends | Skip]","low":0.1,"trend":2,"avg1":2,"avg7":2,"avg30":2,"trend_holo":1.78,"low_holo":0.1},{"id":837491,"name":"Eevee [Colorful Friends | Skip]","low":24.9,"trend":0,"avg1":null,"avg7":null,"avg30":null,"trend_holo":57.3,"low_holo":24.9},{"id":837492,"name":"Vaporeon [Spiral Drain | Fighting Whirlpool]","low":0.7,"trend":0,"avg1":null,"avg7":null,"avg30":null,"trend_holo":2.44,"low_holo":0.7},{"id":837493,"name":"Vaporeon [Spiral Drain | Fighting Whirlpool]","low":12,"trend":0,"avg1":null,"avg7":null,"avg30":null,"trend_holo":33.3,"low_holo":12},{"id":837494,"name":"Jolteon [Linear Attack | Fighting Lightning]","low":0.35,"trend":0,"avg1":null,"avg7":null,"avg30":null,"trend_holo":2.24,"low_holo":0.35},{"id":837495,"name":"Jolteon [Linear Attack | Fighting Lightning]","low":19.99,"trend":0,"avg1":null,"avg7":null,"avg30":null,"trend_holo":23.85,"low_holo":19.99},{"id":837496,"name":"Flareon [Destructive Flame | Fighting Blaze]","low":0.65,"trend":0,"avg1":null,"avg7":null,"avg30":null,"trend_holo":2.22,"low_holo":0.65},{"id":837497,"name":"Flareon [Destructive Flame | Fighting Blaze]","low":9.59,"trend":0,"avg1":null,"avg7":null,"avg30":null,"trend_holo":28.45,"low_holo":9.59},{"id":837498,"name":"Porygon [Conversion 4]","low":0.05,"trend":0,"avg1":null,"avg7":null,"avg30":null,"trend_holo":0.57,"low_holo":0.05},{"id":837499,"name":"Porygon [Conversion 4]","low":4.99,"trend":2.5,"avg1":2.5,"avg7":2.5,"avg30":2.5,"trend_holo":13.53,"low_holo":4.99},{"id":837500,"name":"Omanyte [Tentacular Return]","low":0.1,"trend":0,"avg1":null,"avg7":null,"avg30":null,"trend_holo":0.93,"low_holo":0.1},{"id":837501,"name":"Omanyte [Tentacular Return]","low":9.95,"trend":0,"avg1":null,"avg7":null,"avg30":null,"trend_holo":12.48,"low_holo":9.95},{"id":837502,"name":"Omastar [Primordial Tentacles | Aqua Split]","low":0.02,"trend":0,"avg1":null,"avg7":null,"avg30":null,"trend_holo":0.7,"low_holo":0.02},{"id":837503,"name":"Omastar [Primordial Tentacles | Aqua Split]","low":6.5,"trend":0,"avg1":null,"avg7":null,"avg30":null,"trend_holo":18.15,"low_holo":6.5},{"id":837504,"name":"Kabuto [Double Scratch]","low":0.1,"trend":0,"avg1":null,"avg7":null,"avg30":null,"trend_holo":0.5,"low_holo":0.1},{"id":837505,"name":"Kabuto [Double Scratch]","low":9.99,"trend":10,"avg1":10,"avg7":10,"avg30":10,"trend_holo":13.74,"low_holo":9.99},{"id":837506,"name":"Kabutops [Ancient Way | Draining Blade]","low":0.29,"trend":0,"avg1":null,"avg7":null,"avg30":null,"trend_holo":1.07,"low_holo":0.29},{"id":837507,"name":"Kabutops [Ancient Way | Draining Blade]","low":4.79,"trend":0,"avg1":null,"avg7":null,"avg30":null,"trend_holo":13.77,"low_holo":4.79},{"id":837508,"name":"Aerodactyl [Glide | Devolution Ray]","low":0.5,"trend":0,"avg1":null,"avg7":null,"avg30":null,"trend_holo":1.52,"low_holo":0.5},{"id":837509,"name":"Aerodactyl [Glide | Devolution Ray]","low":14.9,"trend":0,"avg1":null,"avg7":null,"avg30":null,"trend_holo":54.34,"low_holo":14.9},{"id":837510,"name":"Snorlax [Voraciousness | Thudding Press]","low":0.07,"trend":0,"avg1":null,"avg7":null,"avg30":null,"trend_holo":0.54,"low_holo":0.07},{"id":837511,"name":"Snorlax [Voraciousness | Thudding Press]","low":9,"trend":0,"avg1":null,"avg7":null,"avg30":null,"trend_holo":37.37,"low_holo":9},{"id":837512,"name":"Articuno [Ice Float | Blizzard]","low":0.75,"trend":0,"avg1":null,"avg7":null,"avg30":null,"trend_holo":1.61,"low_holo":0.75},{"id":837513,"name":"Articuno [Ice Float | Blizzard]","low":4.5,"trend":0,"avg1":null,"avg7":null,"avg30":null,"trend_holo":15.94,"low_holo":4.5},{"id":837514,"name":"Moltres [Flare Float | Blazing Flight]","low":0.19,"trend":0,"avg1":null,"avg7":null,"avg30":null,"trend_holo":1.76,"low_holo":0.19},{"id":837515,"name":"Moltres [Flare Float | Blazing Flight]","low":8.88,"trend":0,"avg1":null,"avg7":null,"avg30":null,"trend_holo":8.46,"low_holo":8.88},{"id":837516,"name":"Dratini [Beat | Draconic Whip]","low":0.04,"trend":0,"avg1":null,"avg7":null,"avg30":null,"trend_holo":1.07,"low_holo":0.04},{"id":837517,"name":"Dratini [Beat | Draconic Whip]","low":4.79,"trend":0,"avg1":null,"avg7":null,"avg30":null,"trend_holo":20.93,"low_holo":4.79},{"id":837518,"name":"Dragonair [Beat | Aqua Slash]","low":0.24,"trend":0,"avg1":null,"avg7":null,"avg30":null,"trend_holo":1.65,"low_holo":0.24},{"id":837519,"name":"Dragonair [Beat | Aqua Slash]","low":13,"trend":0,"avg1":null,"avg7":null,"avg30":null,"trend_holo":23.83,"low_holo":13},{"id":837520,"name":"Dragonite [Jet Cruise | Dragon Pulse]","low":0.75,"trend":0,"avg1":null,"avg7":null,"avg30":null,"trend_holo":12.89,"low_holo":0.75},{"id":837521,"name":"Dragonite [Jet Cruise | Dragon Pulse]","low":20,"trend":0,"avg1":null,"avg7":null,"avg30":null,"trend_holo":65.12,"low_holo":20},{"id":837522,"name":"Mewtwo [Reflective Barrier | Psyslash]","low":2.99,"trend":0,"avg1":null,"avg7":null,"avg30":null,"trend_holo":4.02,"low_holo":2.99},{"id":837523,"name":"Mewtwo [Reflective Barrier | Psyslash]","low":23,"trend":0,"avg1":null,"avg7":null,"avg30":null,"trend_holo":94.55,"low_holo":23},{"id":837524,"name":"Energy Sticker","low":0.1,"trend":0,"avg1":null,"avg7":null,"avg30":null,"trend_holo":0.85,"low_holo":0.1},{"id":837525,"name":"Energy Sticker","low":2.5,"trend":0,"avg1":null,"avg7":null,"avg30":null,"trend_holo":11.14,"low_holo":2.5},{"id":837526,"name":"Grabber","low":0.09,"trend":0,"avg1":null,"avg7":null,"avg30":null,"trend_holo":0.75,"low_holo":0.09},{"id":837527,"name":"Grabber","low":4,"trend":0,"avg1":null,"avg7":null,"avg30":null,"trend_holo":11.15,"low_holo":4},{"id":837528,"name":"Antique Helix Fossil [Helical Swell]","low":0.04,"trend":0,"avg1":null,"avg7":null,"avg30":null,"trend_holo":0.47,"low_holo":0.04},{"id":837529,"name":"Antique Helix Fossil [Helical Swell]","low":4,"trend":2,"avg1":2,"avg7":2,"avg30":2,"trend_holo":12.51,"low_holo":4},{"id":837530,"name":"Antique Dome Fossil [Domed Armor]","low":0.04,"trend":0,"avg1":null,"avg7":null,"avg30":null,"trend_holo":0.51,"low_holo":0.04},{"id":837531,"name":"Antique Dome Fossil [Domed Armor]","low":3.99,"trend":0,"avg1":null,"avg7":null,"avg30":null,"trend_holo":8.21,"low_holo":3.99},{"id":837532,"name":"Antique Old Amber [Amber Protection]","low":0.04,"trend":0,"avg1":null,"avg7":null,"avg30":null,"trend_holo":0.66,"low_holo":0.04},{"id":837533,"name":"Antique Old Amber [Amber Protection]","low":4.75,"trend":0,"avg1":null,"avg7":null,"avg30":null,"trend_holo":9.94,"low_holo":4.75},{"id":837534,"name":"Protective Goggles","low":0.02,"trend":0,"avg1":null,"avg7":null,"avg30":null,"trend_holo":0.36,"low_holo":0.02},{"id":837535,"name":"Protective Goggles","low":4.49,"trend":0,"avg1":null,"avg7":null,"avg30":null,"trend_holo":7.73,"low_holo":4.49},{"id":837536,"name":"Big Air Balloon","low":0.02,"trend":0,"avg1":null,"avg7":null,"avg30":null,"trend_holo":0.28,"low_holo":0.02},{"id":837537,"name":"Big Air Balloon","low":1.2,"trend":0,"avg1":null,"avg7":null,"avg30":null,"trend_holo":6.7,"low_holo":1.2},{"id":837538,"name":"Rigid Band","low":0.02,"trend":0,"avg1":null,"avg7":null,"avg30":null,"trend_holo":0.2,"low_holo":0.02},{"id":837539,"name":"Rigid Band","low":1.5,"trend":0,"avg1":null,"avg7":null,"avg30":null,"trend_holo":6.88,"low_holo":1.5},{"id":837540,"name":"Leftovers","low":0.02,"trend":1,"avg1":1,"avg7":1,"avg30":1,"trend_holo":0.12,"low_holo":0.02},{"id":837541,"name":"Leftovers","low":0.99,"trend":2,"avg1":2,"avg7":2,"avg30":2,"trend_holo":3.12,"low_holo":0.99},{"id":837542,"name":"Erika's Invitation","low":0.04,"trend":0,"avg1":null,"avg7":null,"avg30":null,"trend_holo":0.29,"low_holo":0.04},{"id":837543,"name":"Erika's Invitation","low":14.99,"trend":0,"avg1":null,"avg7":null,"avg30":null,"trend_holo":44.12,"low_holo":14.99},{"id":837544,"name":"Giovanni's Charisma","low":0.08,"trend":0,"avg1":null,"avg7":null,"avg30":null,"trend_holo":0.19,"low_holo":0.08},{"id":837545,"name":"Giovanni's Charisma","low":5.99,"trend":0,"avg1":null,"avg7":null,"avg30":null,"trend_holo":17.84,"low_holo":5.99},{"id":837546,"name":"Daisy's Help","low":0.05,"trend":0,"avg1":null,"avg7":null,"avg30":null,"trend_holo":0.7,"low_holo":0.05},{"id":837547,"name":"Daisy's Help","low":5,"trend":0,"avg1":null,"avg7":null,"avg30":null,"trend_holo":11.22,"low_holo":5},{"id":837548,"name":"Bill's Transfer","low":0.05,"trend":0,"avg1":null,"avg7":null,"avg30":null,"trend_holo":0.52,"low_holo":0.05},{"id":837549,"name":"Bill's Transfer","low":2.2,"trend":0,"avg1":null,"avg7":null,"avg30":null,"trend_holo":14.37,"low_holo":2.2},{"id":837550,"name":"Cycling Road","low":0.09,"trend":0,"avg1":null,"avg7":null,"avg30":null,"trend_holo":0.68,"low_holo":0.09},{"id":837551,"name":"Cycling Road","low":2,"trend":0,"avg1":null,"avg7":null,"avg30":null,"trend_holo":4.95,"low_holo":2}]}