{"expansion":"expansion-6357","updated":"2026-07-13T02:43:59+0200","cards":[{"id":854460,"name":"Charizard [Battle Sense | Royal Blaze]","low":16.89,"trend":16.51,"avg1":16,"avg7":16.35,"avg30":15.09,"trend_holo":0,"low_holo":null},{"id":854461,"name":"Flaaffy [Dynamotor | Electro Ball]","low":3,"trend":3.37,"avg1":3.98,"avg7":3.89,"avg30":4.29,"trend_holo":0,"low_holo":null},{"id":854462,"name":"Zekrom [Slash | Wild Shock]","low":6,"trend":10.72,"avg1":11.99,"avg7":10.05,"avg30":9.81,"trend_holo":0,"low_holo":null},{"id":854463,"name":"Dedenne [Dede-Flash]","low":3.5,"trend":4.29,"avg1":4.49,"avg7":4.26,"avg30":4.05,"trend_holo":0,"low_holo":null},{"id":854464,"name":"Alcremie [Additional Order | Rainbow Flavor]","low":2,"trend":2.35,"avg1":2.3,"avg7":2.33,"avg30":2.38,"trend_holo":0,"low_holo":null},{"id":854465,"name":"Wyrdeer [Hurried Gait | Extrasensory]","low":1.5,"trend":2.25,"avg1":2.5,"avg7":2.19,"avg30":3.01,"trend_holo":0,"low_holo":null},{"id":854466,"name":"Kleavor [Timber Cleave | Berserker Tackle]","low":2,"trend":2.68,"avg1":2.39,"avg7":2.36,"avg30":2.4,"trend_holo":0,"low_holo":null},{"id":854467,"name":"Ariados [Spider Net | Poison Sting]","low":1.75,"trend":2.64,"avg1":1.99,"avg7":2.09,"avg30":2.58,"trend_holo":0,"low_holo":null},{"id":854468,"name":"Spiritomb [Cursed Message | Chain of Spirits]","low":2,"trend":2.78,"avg1":3,"avg7":2.8,"avg30":2.59,"trend_holo":0,"low_holo":null},{"id":854469,"name":"Galarian Obstagoon [Untamed Shout | Obstruct]","low":2.7,"trend":3.92,"avg1":4.9,"avg7":3.52,"avg30":3.15,"trend_holo":0,"low_holo":null},{"id":854470,"name":"Druddigon [Revenge | Dragon Claw]","low":3.5,"trend":4.03,"avg1":3.79,"avg7":4.03,"avg30":4.46,"trend_holo":0,"low_holo":null},{"id":854471,"name":"Hoothoot [Stand Sentry | Flap]","low":4.5,"trend":5.16,"avg1":5.99,"avg7":5.39,"avg30":5.35,"trend_holo":0,"low_holo":null},{"id":854472,"name":"Pikachu [Pika Dash | Whimsy Tackle]","low":64.89,"trend":66.15,"avg1":68.49,"avg7":65.81,"avg30":64.46,"trend_holo":0,"low_holo":null}]}