{"expansion":"Imprison! Gardevoir ex Constructed Standard Deck","updated":"2026-07-23T02:50:28+0200","cards":[{"id":761932,"name":"Jynx \u03b4 Delta Species [Stages of Evolution | Fire Punch]","low":1.4,"trend":3.72,"avg1":4.5,"avg7":3.54,"avg30":3.54,"trend_holo":0,"low_holo":null},{"id":761933,"name":"Smoochum \u03b4 Delta Species [Baby Evolution | Alluring Kiss]","low":0.95,"trend":5.54,"avg1":6,"avg7":4.5,"avg30":4.5,"trend_holo":0,"low_holo":null},{"id":761934,"name":"Ralts \u03b4 Delta Species [Calm Mind | Will-o'-the-wisp]","low":2.22,"trend":2.36,"avg1":6.99,"avg7":1.7,"avg30":2.49,"trend_holo":0,"low_holo":null},{"id":761935,"name":"Kirlia \u03b4 Delta Species [Flickering Flames | Smack]","low":0.55,"trend":2.47,"avg1":5.99,"avg7":1.43,"avg30":2.15,"trend_holo":0,"low_holo":null},{"id":761936,"name":"Gardevoir ex \u03b4 Delta Species [Imprison | Flame Ball]","low":7,"trend":18.99,"avg1":35.5,"avg7":23.21,"avg30":17.28,"trend_holo":0,"low_holo":null},{"id":761937,"name":"Smeargle \u03b4 Delta Species [Collect | Flickering Tail]","low":0.5,"trend":3.28,"avg1":1.35,"avg7":2.79,"avg30":2.79,"trend_holo":0,"low_holo":null},{"id":761938,"name":"Ralts [Hypnosis | Psychic Boom]","low":1.77,"trend":3.87,"avg1":4.49,"avg7":3.12,"avg30":3.12,"trend_holo":0,"low_holo":null},{"id":761939,"name":"Kirlia [Psyshock | Link Blast]","low":2.22,"trend":0.5,"avg1":0.5,"avg7":1.75,"avg30":1.75,"trend_holo":0,"low_holo":null},{"id":761940,"name":"Trapinch \u03b4 Delta Species [Gnaw | Dig]","low":0.55,"trend":1.71,"avg1":0.95,"avg7":1.24,"avg30":1.17,"trend_holo":0,"low_holo":null},{"id":761941,"name":"Vibrava \u03b4 Delta Species [Bite | Sonic Noise]","low":1.44,"trend":4.41,"avg1":5,"avg7":3.74,"avg30":3.74,"trend_holo":0,"low_holo":null},{"id":761942,"name":"Potion","low":0.6,"trend":0.2,"avg1":0.2,"avg7":0.2,"avg30":0.2,"trend_holo":0,"low_holo":null},{"id":761943,"name":"Dual Ball","low":0.95,"trend":0.25,"avg1":0.25,"avg7":0.25,"avg30":0.25,"trend_holo":0,"low_holo":null},{"id":761944,"name":"Old Rod","low":2,"trend":null,"avg1":null,"avg7":null,"avg30":null},{"id":761945,"name":"Professor Elm's Training Method","low":null,"trend":6.44,"avg1":7,"avg7":4.22,"avg30":4.22,"trend_holo":0,"low_holo":null},{"id":761946,"name":"Scott","low":1.5,"trend":null,"avg1":null,"avg7":null,"avg30":null},{"id":761947,"name":"Professor Oak's Research","low":1.45,"trend":0.2,"avg1":0.2,"avg7":0.2,"avg30":0.2,"trend_holo":0,"low_holo":null},{"id":761948,"name":"Professor Birch","low":0.3,"trend":null,"avg1":null,"avg7":null,"avg30":null},{"id":761949,"name":"Island Hermit","low":3.49,"trend":2.49,"avg1":2.49,"avg7":2.49,"avg30":2.49,"trend_holo":0,"low_holo":null},{"id":761950,"name":"Mr. Stone's Project","low":13.99,"trend":4.49,"avg1":4.49,"avg7":4.49,"avg30":4.49,"trend_holo":0,"low_holo":null},{"id":761951,"name":"Celio's Network","low":1,"trend":0.2,"avg1":0.2,"avg7":0.2,"avg30":0.2,"trend_holo":0,"low_holo":null},{"id":761952,"name":"Fieldworker","low":2,"trend":9.49,"avg1":9.49,"avg7":9.49,"avg30":9.49,"trend_holo":0,"low_holo":null},{"id":761953,"name":"Bill's Maintenance","low":0.95,"trend":null,"avg1":null,"avg7":null,"avg30":null},{"id":761954,"name":"Buffer Piece","low":0.3,"trend":null,"avg1":null,"avg7":null,"avg30":null},{"id":761955,"name":"Rainbow Energy Delta","low":0.49,"trend":2.72,"avg1":2.72,"avg7":2.72,"avg30":2.72,"trend_holo":0,"low_holo":null}]}